crds/__init__.py
crds/_version.py
crds/data_file.py
crds/diff.py
crds/list.py
crds/matches.py
crds/rowdiff.py
crds/sync.py
crds/uses.py
crds/bestrefs/__init__.py
crds/bestrefs/__main__.py
crds/bestrefs/bestrefs.py
crds/bestrefs/headers.py
crds/bestrefs/stale.py
crds/bestrefs/table_effects.py
crds/certify/__init__.py
crds/certify/__main__.py
crds/certify/certify.py
crds/certify/check_sha1sum.py
crds/certify/mapping_parser.py
crds/certify/validators/__init__.py
crds/certify/validators/core.py
crds/certify/validators/helpers.py
crds/certify/validators/synphot.py
crds/client/__init__.py
crds/client/api.py
crds/client/proxy.py
crds/core/__init__.py
crds/core/cmdline.py
crds/core/config.py
crds/core/constants.py
crds/core/crds_cache_locking.py
crds/core/custom_dict.py
crds/core/exceptions.py
crds/core/generic_tpn.py
crds/core/git_version.py
crds/core/heavy_client.py
crds/core/log.py
crds/core/mapping_verifier.py
crds/core/naming.py
crds/core/pysh.py
crds/core/python23.py
crds/core/reftypes.py
crds/core/rmap.py
crds/core/selectors.py
crds/core/substitutions.py
crds/core/timestamp.py
crds/core/utils.py
crds/hst/__init__.py
crds/hst/__main__.py
crds/hst/acs.py
crds/hst/acs_common.py
crds/hst/acs_v1.py
crds/hst/acs_v2.py
crds/hst/acs_v3.py
crds/hst/cos.py
crds/hst/locate.py
crds/hst/nicmos.py
crds/hst/siname.py
crds/hst/stis.py
crds/hst/substitutions.dat
crds/hst/synphot.py
crds/hst/wfc3.py
crds/hst/wfpc2.py
crds/hst/specs/acs_atodtab.spec
crds/hst/specs/acs_biasfile.spec
crds/hst/specs/acs_bpixtab.spec
crds/hst/specs/acs_ccdtab.spec
crds/hst/specs/acs_cfltfile.spec
crds/hst/specs/acs_crrejtab.spec
crds/hst/specs/acs_d2imfile.spec
crds/hst/specs/acs_darkfile.spec
crds/hst/specs/acs_dfltfile.rmap
crds/hst/specs/acs_dgeofile.spec
crds/hst/specs/acs_drkcfile.spec
crds/hst/specs/acs_flshfile.spec
crds/hst/specs/acs_idctab.spec
crds/hst/specs/acs_imphttab.spec
crds/hst/specs/acs_lfltfile.spec
crds/hst/specs/acs_mdriztab.spec
crds/hst/specs/acs_mlintab.spec
crds-13.1.0.dist-info/licenses/LICENSE
crds-13.1.0.dist-info/METADATA
crds-13.1.0.dist-info/WHEEL
crds-13.1.0.dist-info/top_level.txt
crds-13.1.0.dist-info/RECORD
