Metadata-Version: 2.4
Name: crds
Version: 13.1.0
Summary: Calibration Reference Data System,  HST/JWST/Roman reference file management
Author: STScI CRDS s/w developers
Project-URL: homepage, https://github.com/spacetelescope/crds
Platform: Linux
Platform: OS-X
Classifier: Intended Audience :: Science/Research
Classifier: Operating System :: POSIX :: Linux
Classifier: Operating System :: MacOS :: MacOS X
Classifier: Programming Language :: Python :: 3
Classifier: Topic :: Scientific/Engineering :: Astronomy
Requires-Python: >=3.7
License-File: LICENSE
Requires-Dist: astropy
Requires-Dist: numpy
Requires-Dist: filelock
Requires-Dist: asdf!=3.0.0
Requires-Dist: requests
Requires-Dist: parsley
Provides-Extra: jwst
Requires-Dist: jwst; extra == "jwst"
Provides-Extra: roman
Requires-Dist: roman_datamodels; extra == "roman"
Provides-Extra: submission
Requires-Dist: bs4; extra == "submission"
Provides-Extra: dev
Requires-Dist: ipython; extra == "dev"
Requires-Dist: jupyterlab; extra == "dev"
Requires-Dist: ansible; extra == "dev"
Requires-Dist: helm; extra == "dev"
Provides-Extra: test
Requires-Dist: mock; extra == "test"
Requires-Dist: pytest>=6.0; extra == "test"
Requires-Dist: pytest-astropy; extra == "test"
Requires-Dist: pytest-doctestplus>=0.10.0; extra == "test"
Requires-Dist: stsynphot; extra == "test"
Requires-Dist: stdatamodels; extra == "test"
Provides-Extra: docs
Requires-Dist: sphinx; extra == "docs"
Requires-Dist: sphinx_rtd_theme; extra == "docs"
Requires-Dist: docutils; extra == "docs"
Requires-Dist: sphinx_automodapi; extra == "docs"
Requires-Dist: sphinx-tabs; extra == "docs"
Requires-Dist: sphinx-copybutton; extra == "docs"
Provides-Extra: aws
Requires-Dist: boto3; extra == "aws"
Requires-Dist: awscli; extra == "aws"
Provides-Extra: synphot
Requires-Dist: stsynphot; extra == "synphot"
Dynamic: license-file
